ALU.v
module ALU (
    input [7:0] A,
    input [7:0] B,
    input [3:0] OpCode,
    output reg [7:0] Result,
    output reg Carry,
    output reg Zero,
    output reg Overflow,
    output reg Parity
);

always @(*) begin
    Carry = 0;
    Zero = 0;
    Overflow = 0;
    Parity = 0;

    case (OpCode)
        4'b0000: Result = A + B;
        4'b0001: Result = A - B;
        4'b0010: Result = A & B;
        4'b0011: Result = A | B;
        4'b0100: Result = A ^ B;
        4'b0101: Result = ~A;
        4'b0110: Result = A << 1;
        4'b0111: Result = A >> 1;
        4'b1000: Result = {A[6:0], 1'b0};
        4'b1001: Result = {1'b0, A[7:1]};
        4'b1010: Result = (A == B) ? 8'b1 : 8'b0;
        4'b1011: Result = (A < B) ? 8'b1 : 8'b0;
        4'b1100: Result = A * B;
        4'b1101: Result = A / B;
        4'b1110: Result = A % B;
        4'b1111: Result = (A < 8'h80) ? (A << 1) : (A >> 1);
        default: Result = 8'b00000000;
    endcase

    Carry = (OpCode == 4'b0000) && (A + B > 8'hFF);
    Zero = (Result == 8'b0);
    Overflow = (OpCode == 4'b0000) && ((A[7] == B[7]) && (Result[7] != A[7]));
    Parity = ~(^Result);
end

endmodule

ALU_testbench.v
module ALU_testbench;

reg [7:0] A, B;
reg [3:0] OpCode;
wire [7:0] Result;
wire Carry, Zero, Overflow, Parity;

ALU alu_inst (
    .A(A),
    .B(B),
    .OpCode(OpCode),
    .Result(Result),
    .Carry(Carry),
    .Zero(Zero),
    .Overflow(Overflow),
    .Parity(Parity)
);

initial begin
    $dumpfile("ALU_waveform.vcd");
    $dumpvars(0, alu_inst);
end

initial begin
    A = 8'h12;
    B = 8'h34;
    OpCode = 4'b0000;
    #10;

    A = 8'hFF;
    B = 8'h01;
    OpCode = 4'b0000;
    #10;

    A = 8'h34;
    B = 8'h12;
    OpCode = 4'b0001;
    #10;

    A = 8'h12;
    B = 8'h34;
    OpCode = 4'b0001;
    #10;

    A = 8'hAA;
    B = 8'h55;
    OpCode = 4'b0010;
    #10;

    A = 8'h0F;
    B = 8'hF0;
    OpCode = 4'b0011;
    #10;

    A = 8'hFF;
    B = 8'h0F;
    OpCode = 4'b0100;
    #10;

    A = 8'hFF;
    OpCode = 4'b0101;
    #10;

    A = 8'h01;
    OpCode = 4'b0110;
    #10;

    A = 8'h80;
    OpCode = 4'b0111;
    #10;

    A = 8'h85;
    OpCode = 4'b1000;
    #10;

    A = 8'h85;
    OpCode = 4'b1001;
    #10;

    A = 8'h12;
    B = 8'h12;
    OpCode = 4'b1010;
    #10;

    A = 8'h12;
    B = 8'h34;
    OpCode = 4'b1011;
    #10;

    A = 8'h04;
    B = 8'h03;
    OpCode = 4'b1100;
    #10;

    A = 8'h08;
    B = 8'h02;
    OpCode = 4'b1101;
    #10;

    A = 8'h08;
    B = 8'h00;
    OpCode = 4'b1101;
    #10;

    A = 8'h09;
    B = 8'h04;
    OpCode = 4'b1110;
    #10;

    A = 8'h40;
    OpCode = 4'b1111;
    #10;

    A = 8'hC0;
    OpCode = 4'b1111;
    #10;

    $stop;
end

endmodule

ALU_waveform.vcd
$date
	Sat Mar 28 17:21:21 2026
$end
$version
	Icarus Verilog
$end
$timescale
	1s
$end
$scope module ALU_testbench $end
$scope module alu_inst $end
$var wire 8 ! A [7:0] $end
$var wire 8 " B [7:0] $end
$var wire 4 # OpCode [3:0] $end
$var reg 1 $ Carry $end
$var reg 1 % Overflow $end
$var reg 1 & Parity $end
$var reg 8 ' Result [7:0] $end
$var reg 1 ( Zero $end
$upscope $end
$upscope $end
$enddefinitions $end
$comment Show the parameter values. $end
$dumpall
$end
#0
$dumpvars
0(
b1000110 '
0&
0%
0$
b0 #
b110100 "
b10010 !
$end
#10
1&
1(
b0 '
b1 "
b11111111 !
#20
b100010 '
1&
0(
b1 #
b10010 "
b110100 !
#30
b11011110 '
1&
b110100 "
b10010 !
#40
1(
b0 '
1&
b10 #
b1010101 "
b10101010 !
#50
b11111111 '
1&
0(
b11 #
b11110000 "
b1111 !
#60
b11110000 '
1&
b100 #
b1111 "
b11111111 !
#70
1(
b0 '
1&
b101 #
#80
b10 '
0&
0(
b110 #
b1 !
#90
b1000000 '
b111 #
b10000000 !
#100
1&
b1010 '
b1000 #
b10000101 !
#110
b1000010 '
1&
b1001 #
#120
b1 '
0&
b1010 #
b10010 "
b10010 !
#130
b1011 #
b110100 "
#140
1&
b1100 '
b1100 #
b11 "
b100 !
#150
b100 '
0&
b1101 #
b10 "
b1000 !
#160
x&
x(
bx '
b0 "
#170
b1 '
0&
0(
b1110 #
b100 "
b1001 !
#180
b10000000 '
b1111 #
b1000000 !
#190
1&
b1100000 '
b11000000 !
